[
    {
        "liens": {
            "https://le-recensement-et-moi.fr#main": "https://le-recensement-et-moi.fr",
            "https://le-recensement-et-moi.fr/": "https://le-recensement-et-moi.fr",
            "https://le-recensement-et-moi.fr/accessibilite": "https://le-recensement-et-moi.fr",
            "https://le-recensement-et-moi.fr/cest-simple": "https://le-recensement-et-moi.fr",
            "https://le-recensement-et-moi.fr/cest-simple/": "https://le-recensement-et-moi.fr",
            "https://le-recensement-et-moi.fr/cest-sur": "https://le-recensement-et-moi.fr",
            "https://le-recensement-et-moi.fr/cest-sur/": "https://le-recensement-et-moi.fr",
            "https://le-recensement-et-moi.fr/cest-utile": "https://le-recensement-et-moi.fr",
            "https://le-recensement-et-moi.fr/cest-utile/": "https://le-recensement-et-moi.fr",
            "https://le-recensement-et-moi.fr/homologation": "https://le-recensement-et-moi.fr",
            "https://le-recensement-et-moi.fr/mentions-legales": "https://le-recensement-et-moi.fr",
            "https://le-recensement-et-moi.fr/plan-du-site": "https://le-recensement-et-moi.fr",
            "https://le-recensement-et-moi.fr/repondre-en-ligne-au-recensement-de-la-population": "https://le-recensement-et-moi.fr",
            "https://le-recensement-et-moi.fr/reponses": "https://le-recensement-et-moi.fr",
            "https://le-recensement-et-moi.fr/reponses/": "https://le-recensement-et-moi.fr",
            "https://le-recensement-et-moi.fr/rgpd": "https://le-recensement-et-moi.fr"
        },
        "premier_paragraphe": "République\n                  Française",
        "titre": "Accueil – Le recensement de la population 2025 | INSEE",
        "url": "https://le-recensement-et-moi.fr"
    },
    {
        "liens": {
            "https://le-recensement-et-moi.fr#main": "https://le-recensement-et-moi.fr#main",
            "https://le-recensement-et-moi.fr/": "https://le-recensement-et-moi.fr#main",
            "https://le-recensement-et-moi.fr/accessibilite": "https://le-recensement-et-moi.fr#main",
            "https://le-recensement-et-moi.fr/cest-simple": "https://le-recensement-et-moi.fr#main",
            "https://le-recensement-et-moi.fr/cest-simple/": "https://le-recensement-et-moi.fr#main",
            "https://le-recensement-et-moi.fr/cest-sur": "https://le-recensement-et-moi.fr#main",
            "https://le-recensement-et-moi.fr/cest-sur/": "https://le-recensement-et-moi.fr#main",
            "https://le-recensement-et-moi.fr/cest-utile": "https://le-recensement-et-moi.fr#main",
            "https://le-recensement-et-moi.fr/cest-utile/": "https://le-recensement-et-moi.fr#main",
            "https://le-recensement-et-moi.fr/homologation": "https://le-recensement-et-moi.fr#main",
            "https://le-recensement-et-moi.fr/mentions-legales": "https://le-recensement-et-moi.fr#main",
            "https://le-recensement-et-moi.fr/plan-du-site": "https://le-recensement-et-moi.fr#main",
            "https://le-recensement-et-moi.fr/repondre-en-ligne-au-recensement-de-la-population": "https://le-recensement-et-moi.fr#main",
            "https://le-recensement-et-moi.fr/reponses": "https://le-recensement-et-moi.fr#main",
            "https://le-recensement-et-moi.fr/reponses/": "https://le-recensement-et-moi.fr#main",
            "https://le-recensement-et-moi.fr/rgpd": "https://le-recensement-et-moi.fr#main"
        },
        "premier_paragraphe": "République\n                  Française",
        "titre": "Accueil – Le recensement de la population 2025 | INSEE",
        "url": "https://le-recensement-et-moi.fr#main"
    },
    {
        "liens": {
            "https://le-recensement-et-moi.fr/": "https://le-recensement-et-moi.fr/",
            "https://le-recensement-et-moi.fr/#main": "https://le-recensement-et-moi.fr/",
            "https://le-recensement-et-moi.fr/accessibilite": "https://le-recensement-et-moi.fr/",
            "https://le-recensement-et-moi.fr/cest-simple": "https://le-recensement-et-moi.fr/",
            "https://le-recensement-et-moi.fr/cest-simple/": "https://le-recensement-et-moi.fr/",
            "https://le-recensement-et-moi.fr/cest-sur": "https://le-recensement-et-moi.fr/",
            "https://le-recensement-et-moi.fr/cest-sur/": "https://le-recensement-et-moi.fr/",
            "https://le-recensement-et-moi.fr/cest-utile": "https://le-recensement-et-moi.fr/",
            "https://le-recensement-et-moi.fr/cest-utile/": "https://le-recensement-et-moi.fr/",
            "https://le-recensement-et-moi.fr/homologation": "https://le-recensement-et-moi.fr/",
            "https://le-recensement-et-moi.fr/mentions-legales": "https://le-recensement-et-moi.fr/",
            "https://le-recensement-et-moi.fr/plan-du-site": "https://le-recensement-et-moi.fr/",
            "https://le-recensement-et-moi.fr/repondre-en-ligne-au-recensement-de-la-population": "https://le-recensement-et-moi.fr/",
            "https://le-recensement-et-moi.fr/reponses": "https://le-recensement-et-moi.fr/",
            "https://le-recensement-et-moi.fr/reponses/": "https://le-recensement-et-moi.fr/",
            "https://le-recensement-et-moi.fr/rgpd": "https://le-recensement-et-moi.fr/"
        },
        "premier_paragraphe": "République\n                  Française",
        "titre": "Accueil – Le recensement de la population 2025 | INSEE",
        "url": "https://le-recensement-et-moi.fr/"
    },
    {
        "liens": {
            "https://le-recensement-et-moi.fr/": "https://le-recensement-et-moi.fr/cest-utile",
            "https://le-recensement-et-moi.fr/accessibilite": "https://le-recensement-et-moi.fr/cest-utile",
            "https://le-recensement-et-moi.fr/cest-simple": "https://le-recensement-et-moi.fr/cest-utile",
            "https://le-recensement-et-moi.fr/cest-sur": "https://le-recensement-et-moi.fr/cest-utile",
            "https://le-recensement-et-moi.fr/cest-utile": "https://le-recensement-et-moi.fr/cest-utile",
            "https://le-recensement-et-moi.fr/cest-utile#main": "https://le-recensement-et-moi.fr/cest-utile",
            "https://le-recensement-et-moi.fr/homologation": "https://le-recensement-et-moi.fr/cest-utile",
            "https://le-recensement-et-moi.fr/importance-de-participer-au-recensement": "https://le-recensement-et-moi.fr/cest-utile",
            "https://le-recensement-et-moi.fr/le-recensement-a-quoi-ca-sert": "https://le-recensement-et-moi.fr/cest-utile",
            "https://le-recensement-et-moi.fr/mentions-legales": "https://le-recensement-et-moi.fr/cest-utile",
            "https://le-recensement-et-moi.fr/personne-agee": "https://le-recensement-et-moi.fr/cest-utile",
            "https://le-recensement-et-moi.fr/petite-enfance": "https://le-recensement-et-moi.fr/cest-utile",
            "https://le-recensement-et-moi.fr/plan-du-site": "https://le-recensement-et-moi.fr/cest-utile",
            "https://le-recensement-et-moi.fr/question-recensement": "https://le-recensement-et-moi.fr/cest-utile",
            "https://le-recensement-et-moi.fr/reponses": "https://le-recensement-et-moi.fr/cest-utile",
            "https://le-recensement-et-moi.fr/rgpd": "https://le-recensement-et-moi.fr/cest-utile"
        },
        "premier_paragraphe": "République\n                  Française",
        "titre": "C'est utile – Le recensement de la population 2025 | INSEE",
        "url": "https://le-recensement-et-moi.fr/cest-utile"
    },
    {
        "liens": {
            "https://le-recensement-et-moi.fr/": "https://le-recensement-et-moi.fr/cest-simple",
            "https://le-recensement-et-moi.fr/accessibilite": "https://le-recensement-et-moi.fr/cest-simple",
            "https://le-recensement-et-moi.fr/cest-simple": "https://le-recensement-et-moi.fr/cest-simple",
            "https://le-recensement-et-moi.fr/cest-simple#main": "https://le-recensement-et-moi.fr/cest-simple",
            "https://le-recensement-et-moi.fr/cest-simple/documentDuRecensement": "https://le-recensement-et-moi.fr/cest-simple",
            "https://le-recensement-et-moi.fr/cest-simple/fr/etudiant-fr": "https://le-recensement-et-moi.fr/cest-simple",
            "https://le-recensement-et-moi.fr/cest-sur": "https://le-recensement-et-moi.fr/cest-simple",
            "https://le-recensement-et-moi.fr/cest-utile": "https://le-recensement-et-moi.fr/cest-simple",
            "https://le-recensement-et-moi.fr/homologation": "https://le-recensement-et-moi.fr/cest-simple",
            "https://le-recensement-et-moi.fr/le-recensement-comment-ca-marche": "https://le-recensement-et-moi.fr/cest-simple",
            "https://le-recensement-et-moi.fr/le-recensement-concerne-t-il-les-etrangers": "https://le-recensement-et-moi.fr/cest-simple",
            "https://le-recensement-et-moi.fr/le-recensement-des-sans-abris": "https://le-recensement-et-moi.fr/cest-simple",
            "https://le-recensement-et-moi.fr/le-recensement-en-ligne": "https://le-recensement-et-moi.fr/cest-simple",
            "https://le-recensement-et-moi.fr/mentions-legales": "https://le-recensement-et-moi.fr/cest-simple",
            "https://le-recensement-et-moi.fr/modalite-du-recensement": "https://le-recensement-et-moi.fr/cest-simple",
            "https://le-recensement-et-moi.fr/plan-du-site": "https://le-recensement-et-moi.fr/cest-simple",
            "https://le-recensement-et-moi.fr/repondre-en-ligne-au-recensement-de-la-population": "https://le-recensement-et-moi.fr/cest-simple",
            "https://le-recensement-et-moi.fr/reponses": "https://le-recensement-et-moi.fr/cest-simple",
            "https://le-recensement-et-moi.fr/rgpd": "https://le-recensement-et-moi.fr/cest-simple"
        },
        "premier_paragraphe": "République\n                  Française",
        "titre": "C'est Simple – Le recensement de la population 2025 | INSEE",
        "url": "https://le-recensement-et-moi.fr/cest-simple"
    },
    {
        "liens": {
            "https://le-recensement-et-moi.fr/": "https://le-recensement-et-moi.fr/cest-sur",
            "https://le-recensement-et-moi.fr/accessibilite": "https://le-recensement-et-moi.fr/cest-sur",
            "https://le-recensement-et-moi.fr/cest-simple": "https://le-recensement-et-moi.fr/cest-sur",
            "https://le-recensement-et-moi.fr/cest-sur": "https://le-recensement-et-moi.fr/cest-sur",
            "https://le-recensement-et-moi.fr/cest-sur#main": "https://le-recensement-et-moi.fr/cest-sur",
            "https://le-recensement-et-moi.fr/cest-utile": "https://le-recensement-et-moi.fr/cest-sur",
            "https://le-recensement-et-moi.fr/homologation": "https://le-recensement-et-moi.fr/cest-sur",
            "https://le-recensement-et-moi.fr/le-recensement-cest-sur": "https://le-recensement-et-moi.fr/cest-sur",
            "https://le-recensement-et-moi.fr/mentions-legales": "https://le-recensement-et-moi.fr/cest-sur",
            "https://le-recensement-et-moi.fr/plan-du-site": "https://le-recensement-et-moi.fr/cest-sur",
            "https://le-recensement-et-moi.fr/reponses": "https://le-recensement-et-moi.fr/cest-sur",
            "https://le-recensement-et-moi.fr/rgpd": "https://le-recensement-et-moi.fr/cest-sur",
            "https://le-recensement-et-moi.fr/securite-des-donnees": "https://le-recensement-et-moi.fr/cest-sur"
        },
        "premier_paragraphe": "République\n                  Française",
        "titre": "C'est Sûr – Le recensement de la population 2025 | INSEE",
        "url": "https://le-recensement-et-moi.fr/cest-sur"
    },
    {
        "liens": {
            "https://le-recensement-et-moi.fr/": "https://le-recensement-et-moi.fr/reponses",
            "https://le-recensement-et-moi.fr/accessibilite": "https://le-recensement-et-moi.fr/reponses",
            "https://le-recensement-et-moi.fr/cest-simple": "https://le-recensement-et-moi.fr/reponses",
            "https://le-recensement-et-moi.fr/cest-sur": "https://le-recensement-et-moi.fr/reponses",
            "https://le-recensement-et-moi.fr/cest-utile": "https://le-recensement-et-moi.fr/reponses",
            "https://le-recensement-et-moi.fr/homologation": "https://le-recensement-et-moi.fr/reponses",
            "https://le-recensement-et-moi.fr/mentions-legales": "https://le-recensement-et-moi.fr/reponses",
            "https://le-recensement-et-moi.fr/plan-du-site": "https://le-recensement-et-moi.fr/reponses",
            "https://le-recensement-et-moi.fr/reponses": "https://le-recensement-et-moi.fr/reponses",
            "https://le-recensement-et-moi.fr/reponses#main": "https://le-recensement-et-moi.fr/reponses",
            "https://le-recensement-et-moi.fr/rgpd": "https://le-recensement-et-moi.fr/reponses"
        },
        "premier_paragraphe": "République\n                  Française",
        "titre": "Réponses – Le recensement de la population 2025 | INSEE",
        "url": "https://le-recensement-et-moi.fr/reponses"
    },
    {
        "liens": {
            "https://le-recensement-et-moi.fr/": "https://le-recensement-et-moi.fr/repondre-en-ligne-au-recensement-de-la-population",
            "https://le-recensement-et-moi.fr/accessibilite": "https://le-recensement-et-moi.fr/repondre-en-ligne-au-recensement-de-la-population",
            "https://le-recensement-et-moi.fr/cest-simple": "https://le-recensement-et-moi.fr/repondre-en-ligne-au-recensement-de-la-population",
            "https://le-recensement-et-moi.fr/cest-sur": "https://le-recensement-et-moi.fr/repondre-en-ligne-au-recensement-de-la-population",
            "https://le-recensement-et-moi.fr/cest-utile": "https://le-recensement-et-moi.fr/repondre-en-ligne-au-recensement-de-la-population",
            "https://le-recensement-et-moi.fr/homologation": "https://le-recensement-et-moi.fr/repondre-en-ligne-au-recensement-de-la-population",
            "https://le-recensement-et-moi.fr/mentions-legales": "https://le-recensement-et-moi.fr/repondre-en-ligne-au-recensement-de-la-population",
            "https://le-recensement-et-moi.fr/plan-du-site": "https://le-recensement-et-moi.fr/repondre-en-ligne-au-recensement-de-la-population",
            "https://le-recensement-et-moi.fr/repondre-en-ligne-au-recensement-de-la-population#main": "https://le-recensement-et-moi.fr/repondre-en-ligne-au-recensement-de-la-population",
            "https://le-recensement-et-moi.fr/reponses": "https://le-recensement-et-moi.fr/repondre-en-ligne-au-recensement-de-la-population",
            "https://le-recensement-et-moi.fr/rgpd": "https://le-recensement-et-moi.fr/repondre-en-ligne-au-recensement-de-la-population"
        },
        "premier_paragraphe": "République\n                  Française",
        "titre": "Répondre en ligne au recensement de la population – Le recensement de la population 2025 | INSEE",
        "url": "https://le-recensement-et-moi.fr/repondre-en-ligne-au-recensement-de-la-population"
    },
    {
        "liens": {
            "https://le-recensement-et-moi.fr/": "https://le-recensement-et-moi.fr/cest-utile/",
            "https://le-recensement-et-moi.fr/accessibilite": "https://le-recensement-et-moi.fr/cest-utile/",
            "https://le-recensement-et-moi.fr/cest-simple": "https://le-recensement-et-moi.fr/cest-utile/",
            "https://le-recensement-et-moi.fr/cest-sur": "https://le-recensement-et-moi.fr/cest-utile/",
            "https://le-recensement-et-moi.fr/cest-utile": "https://le-recensement-et-moi.fr/cest-utile/",
            "https://le-recensement-et-moi.fr/cest-utile/#main": "https://le-recensement-et-moi.fr/cest-utile/",
            "https://le-recensement-et-moi.fr/cest-utile/importance-de-participer-au-recensement": "https://le-recensement-et-moi.fr/cest-utile/",
            "https://le-recensement-et-moi.fr/cest-utile/le-recensement-a-quoi-ca-sert": "https://le-recensement-et-moi.fr/cest-utile/",
            "https://le-recensement-et-moi.fr/cest-utile/personne-agee": "https://le-recensement-et-moi.fr/cest-utile/",
            "https://le-recensement-et-moi.fr/cest-utile/petite-enfance": "https://le-recensement-et-moi.fr/cest-utile/",
            "https://le-recensement-et-moi.fr/cest-utile/question-recensement": "https://le-recensement-et-moi.fr/cest-utile/",
            "https://le-recensement-et-moi.fr/homologation": "https://le-recensement-et-moi.fr/cest-utile/",
            "https://le-recensement-et-moi.fr/mentions-legales": "https://le-recensement-et-moi.fr/cest-utile/",
            "https://le-recensement-et-moi.fr/plan-du-site": "https://le-recensement-et-moi.fr/cest-utile/",
            "https://le-recensement-et-moi.fr/reponses": "https://le-recensement-et-moi.fr/cest-utile/",
            "https://le-recensement-et-moi.fr/rgpd": "https://le-recensement-et-moi.fr/cest-utile/"
        },
        "premier_paragraphe": "République\n                  Française",
        "titre": "C'est utile – Le recensement de la population 2025 | INSEE",
        "url": "https://le-recensement-et-moi.fr/cest-utile/"
    },
    {
        "liens": {
            "https://le-recensement-et-moi.fr/": "https://le-recensement-et-moi.fr/cest-simple/",
            "https://le-recensement-et-moi.fr/accessibilite": "https://le-recensement-et-moi.fr/cest-simple/",
            "https://le-recensement-et-moi.fr/cest-simple": "https://le-recensement-et-moi.fr/cest-simple/",
            "https://le-recensement-et-moi.fr/cest-simple/#main": "https://le-recensement-et-moi.fr/cest-simple/",
            "https://le-recensement-et-moi.fr/cest-simple/documentDuRecensement": "https://le-recensement-et-moi.fr/cest-simple/",
            "https://le-recensement-et-moi.fr/cest-simple/fr/etudiant-fr": "https://le-recensement-et-moi.fr/cest-simple/",
            "https://le-recensement-et-moi.fr/cest-simple/le-recensement-comment-ca-marche": "https://le-recensement-et-moi.fr/cest-simple/",
            "https://le-recensement-et-moi.fr/cest-simple/le-recensement-concerne-t-il-les-etrangers": "https://le-recensement-et-moi.fr/cest-simple/",
            "https://le-recensement-et-moi.fr/cest-simple/le-recensement-des-sans-abris": "https://le-recensement-et-moi.fr/cest-simple/",
            "https://le-recensement-et-moi.fr/cest-simple/le-recensement-en-ligne": "https://le-recensement-et-moi.fr/cest-simple/",
            "https://le-recensement-et-moi.fr/cest-simple/modalite-du-recensement": "https://le-recensement-et-moi.fr/cest-simple/",
            "https://le-recensement-et-moi.fr/cest-simple/repondre-en-ligne-au-recensement-de-la-population": "https://le-recensement-et-moi.fr/cest-simple/",
            "https://le-recensement-et-moi.fr/cest-sur": "https://le-recensement-et-moi.fr/cest-simple/",
            "https://le-recensement-et-moi.fr/cest-utile": "https://le-recensement-et-moi.fr/cest-simple/",
            "https://le-recensement-et-moi.fr/homologation": "https://le-recensement-et-moi.fr/cest-simple/",
            "https://le-recensement-et-moi.fr/mentions-legales": "https://le-recensement-et-moi.fr/cest-simple/",
            "https://le-recensement-et-moi.fr/plan-du-site": "https://le-recensement-et-moi.fr/cest-simple/",
            "https://le-recensement-et-moi.fr/reponses": "https://le-recensement-et-moi.fr/cest-simple/",
            "https://le-recensement-et-moi.fr/rgpd": "https://le-recensement-et-moi.fr/cest-simple/"
        },
        "premier_paragraphe": "République\n                  Française",
        "titre": "C'est Simple – Le recensement de la population 2025 | INSEE",
        "url": "https://le-recensement-et-moi.fr/cest-simple/"
    }
]